{
  "metadata": {
    "chapter_number": "3.6.12",
    "title": "3.6.12 Копирование учебного плана",
    "source_type": "docx_manual",
    "last_updated": "2025-04-03"
  },
  "content": [
    {
      "id": "chapter_13",
      "title": "3.6.12 Копирование учебного плана",
      "paragraphs": [
        {
          "id": "chapter_13.1",
          "text": "В открывшемся окне укажите тот учебный план, на который нужно скопировать дисциплины старого учебного плана по семстрам.",
          "section": "3.6.12 Копирование учебного плана",
          "keywords": [
            "открывшемся",
            "окне",
            "укажите",
            "учебный",
            "план"
          ]
        }
      ],
      "keywords": []
    }
  ]
}